{
    "Enable_Ads":true,
	"whichAds": 1,// 0 for Admob 1 for Applovin
	"Interstitial_Applovin_ButtonBack":"2fb38336c560d201",
	"ENABLE_ONBACK_ADS":false,
    "Interstitial_Applovin":"1d46654a14c6087d",
    "Mrec_Applovin":"1a8a77c57a0b9234",
    "Banner_Applovin":"5d930e3f717cc30e",
	"admob_inter": "ca-app-pub-3940256099942544/1033173712",
	"admob_banner": "ca-app-pub-3940256099942544/6300978111",
	
        //image cpa 
        "Visibility_image_cpa":false,
       "Url_Image_Cpa":"https://www.google.com/",
       "Image_View_cpa":"https://drive.google.com/uc?export=download&id=1HZSUOA4EQaWyMFcb9UV2IRcHqIDwwJFN",
       
       
       //Popup 
        "Visibility_popup":false,
        "Title_View_popup":"",
        "Url_button_popup":"",
        "Image_View_popup":""
       
       
}
